Workbook

Sheet mercado_acoes
A1: Código Cliente | B1: Nome Cliente | C1: Email Cliente | D1: Operação | E1: Stickes | F1: Preço | G1: Data | H1: Dia | I1: Mês | J1: Ano | K1: Valor padronizado
A2: 30 | B2: Larissa Gomes | C2: larissa.gomes94@exemplo.com | D2: Compra | E2: IGTA3 | F2: 10.3 | G2: 44927 | H2: =DAY(G2) -> 1 | I2: =MONTH(G2) -> 1 | J2: =YEAR(G2) -> 2023 | K2: =STANDARDIZE(F2,'estatística'!$C$2,'estatística'!$H$2) -> 0.1139529
A3: 78 | B3: Gabriela Mendes | C3: gabriela.mendes90@exemplo.com | D3: Venda | E3: VIVT3 | F3: 53.3 | G3: 44927 | H3: =DAY(G3) -> 1 | I3: =MONTH(G3) -> 1 | J3: =YEAR(G3) -> 2023 | K3: =STANDARDIZE(F3,'estatística'!$C$2,'estatística'!$H$2) -> 0.65839453
A4: 50 | B4: Camila Rocha | C4: camila.rocha10@exemplo.com | D4: Compra | E4: LREN3 | F4: 21.69 | G4: 44927 | H4: =DAY(G4) -> 1 | I4: =MONTH(G4) -> 1 | J4: =YEAR(G4) -> 2023 | K4: =STANDARDIZE(F4,'estatística'!$C$2,'estatística'!$H$2) -> 0.25816662
A5: 80 | B5: Beatriz Almeida | C5: beatriz.almeida66@exemplo.com | D5: Venda | E5: PETR4 | F5: 39.74 | G5: 44928 | H5: =DAY(G5) -> 2 | I5: =MONTH(G5) -> 1 | J5: =YEAR(G5) -> 2023 | K5: =STANDARDIZE(F5,'estatística'!$C$2,'estatística'!$H$2) -> 0.4867055
A6: 68 | B6: Sofia Melo | C6: sofia.melo31@exemplo.com | D6: Compra | E6: CSAN3 | F6: 17.96 | G6: 44928 | H6: =DAY(G6) -> 2 | I6: =MONTH(G6) -> 1 | J6: =YEAR(G6) -> 2023 | K6: =STANDARDIZE(F6,'estatística'!$C$2,'estatística'!$H$2) -> 0.21093948
A7: 48 | B7: Sofia Melo | C7: sofia.melo78@exemplo.com | D7: Venda | E7: ABEV3 | F7: 11.95 | G7: 44928 | H7: =DAY(G7) -> 2 | I7: =MONTH(G7) -> 1 | J7: =YEAR(G7) -> 2023 | K7: =STANDARDIZE(F7,'estatística'!$C$2,'estatística'!$H$2) -> 0.13484426
A8: 100 | B8: Lucas Cardoso | C8: lucas.cardoso77@exemplo.com | D8: Compra | E8: ITUB4 | F8: 24.53 | G8: 44928 | H8: =DAY(G8) -> 2 | I8: =MONTH(G8) -> 1 | J8: =YEAR(G8) -> 2023 | K8: =STANDARDIZE(F8,'estatística'!$C$2,'estatística'!$H$2) -> 0.2941251
A9: 30 | B9: Larissa Gomes | C9: larissa.gomes94@exemplo.com | D9: Compra | E9: RENT3 | F9: 46.74 | G9: 44928 | H9: =DAY(G9) -> 2 | I9: =MONTH(G9) -> 1 | J9: =YEAR(G9) -> 2023 | K9: =STANDARDIZE(F9,'estatística'!$C$2,'estatística'!$H$2) -> 0.57533553
A10: 81 | B10: Clara Costa | C10: clara.costa91@exemplo.com | D10: Venda | E10: VALE3 | F10: 65.39 | G10: 44928 | H10: =DAY(G10) -> 2 | I10: =MONTH(G10) -> 1 | J10: =YEAR(G10) -> 2023 | K10: =STANDARDIZE(F10,'estatística'!$C$2,'estatística'!$H$2) -> 0.81147126
A11: 15 | B11: Felipe Ribeiro | C11: felipe.ribeiro44@exemplo.com | D11: Venda | E11: BBAS3 | F11: 56.68 | G11: 44929 | H11: =DAY(G11) -> 3 | I11: =MONTH(G11) -> 1 | J11: =YEAR(G11) -> 2023 | K11: =STANDARDIZE(F11,'estatística'!$C$2,'estatística'!$H$2) -> 0.70119017
A12: 86 | B12: Guilherme Oliveira | C12: guilherme.oliveira36@exemplo.com | D12: Venda | E12: PETR4 | F12: 26.99 | G12: 44929 | H12: =DAY(G12) -> 3 | I12: =MONTH(G12) -> 1 | J12: =YEAR(G12) -> 2023 | K12: =STANDARDIZE(F12,'estatística'!$C$2,'estatística'!$H$2) -> 0.32527222
A13: 60 | B13: Marcos Costa | C13: marcos.costa57@exemplo.com | D13: Venda | E13: VALE3 | F13: 78.94 | G13: 44929 | H13: =DAY(G13) -> 3 | I13: =MONTH(G13) -> 1 | J13: =YEAR(G13) -> 2023 | K13: =STANDARDIZE(F13,'estatística'!$C$2,'estatística'!$H$2) -> 0.98303368
... A2001: 33 | B2001: Gustavo Souza | C2001: gustavo.souza88@exemplo.com | D2001: Compra | E2001: LREN3 | F2001: 20.52 | G2001: 45288 | H2001: =DAY(G2001) -> 28 | I2001: =MONTH(G2001) -> 12 | J2001: =YEAR(G2001) -> 2023 | K2001: =STANDARDIZE(F2001,'estatística'!$C$2,'estatística'!$H$2) -> 0.24335275

Sheet estatística
A1: Estatísticas | B1: soma | C1: mínimo | D1: máximo | E1: média | F1: mediana | G1: moda | H1: intervalo | I1: variancia | J1: desvio padrão | L1: Dados do cliente | M1: Coluna 1
B2: =SUM(mercado_acoes!F:F) -> 50905.24 | C2: =MIN(mercado_acoes!F:F) -> 1.3 | D2: =MAX(mercado_acoes!F:F) -> 80.28 | E2: =AVERAGE(mercado_acoes!F:F) -> 25.45262 | F2: =MEDIAN(mercado_acoes!F:F) -> 19.245 | G2: =MODE(mercado_acoes!F:F) -> 10.71 | H2: =Estatísticas[máximo]-Estatísticas[mínimo] -> 78.98 | I2: =VAR(mercado_acoes!F:F) -> 328.64906 | J2: =STDEV(mercado_acoes!F:F) -> 18.128681 | L2: Código | M2: 78
L3: E-mail | M3: =VLOOKUP(M2,mercado_acoes!A:C,3,0) -> gabriela.mendes90@exemplo.com
L4: Nome | M4: =VLOOKUP(M2,mercado_acoes!A:B,2,0) -> Gabriela Mendes

Sheet cliente
A1: Dados do cliente | B1: Coluna 1 | D1: Dados do cliente | E1: Coluna 1
A2: Código | B2: 78 | D2: E-mail do Cliente | E2: larissa.gomes94@exemplo.com
A3: E-mail | B3: =VLOOKUP(B2,mercado_acoes!A:C,3,0) -> gabriela.mendes90@exemplo.com | D3: Cont Compra e Venda | E3: =COUNTIF(mercado_acoes!C:C,E2) -> 20
A4: Nome | B4: =VLOOKUP(B2,mercado_acoes!A:B,2,0) -> Gabriela Mendes | D4: Soma Compra e Venda | E4: =SUMIF(mercado_acoes!C:C,E2,mercado_acoes!F:F) -> 431.4
D5: Média Compra e Venda | E5: =AVERAGEIF(mercado_acoes!C:C,E2,mercado_acoes!F:F) -> 21.57
D6: Perfil | E6: =IF(E3>=20,"Agressivo",IF(AND(E3>5,E3<19),"Moderado","Conservador")) -> Agressivo

Sheet tendencia_temporal
A1: Ano | B1: Mês | C1: Quantidade de operações | D1: Prev. quantidade de operações mês 12 (dezembro) | E1: Diferença entre Previsão e Valor real
A2: 2023 | B2: {=UNIQUE(mercado_acoes!I2:I2001)} -> 1 | C2: =COUNTIF(mercado_acoes!I2:I2001,B2) -> 152
A3: 2023 | B3: 2 | C3: =COUNTIF(mercado_acoes!I3:I2002,B3) -> 172
A4: 2023 | B4: 3 | C4: =COUNTIF(mercado_acoes!I4:I2003,B4) -> 148
A5: 2023 | B5: 4 | C5: =COUNTIF(mercado_acoes!I5:I2004,B5) -> 169
A6: 2023 | B6: 5 | C6: =COUNTIF(mercado_acoes!I6:I2005,B6) -> 167
A7: 2023 | B7: 6 | C7: =COUNTIF(mercado_acoes!I7:I2006,B7) -> 172
A8: 2023 | B8: 7 | C8: =COUNTIF(mercado_acoes!I8:I2007,B8) -> 158
A9: 2023 | B9: 8 | C9: =COUNTIF(mercado_acoes!I9:I2008,B9) -> 180
A10: 2023 | B10: 9 | C10: =COUNTIF(mercado_acoes!I10:I2009,B10) -> 154
A11: 2023 | B11: 10 | C11: =COUNTIF(mercado_acoes!I11:I2010,B11) -> 156
A12: 2023 | B12: 11 | C12: =COUNTIF(mercado_acoes!I12:I2011,B12) -> 185
A13: 2023 | B13: 12 | C13: =COUNTIF(mercado_acoes!I13:I2012,B13) -> 187 | D13: =FORECAST(B13,C2:C12,B2:B12) -> 172.01818 | E13: =C13-D13 -> 14.981818

Sheet compra_venda

Sheet cliente_compra_venda

Sheet cliente_lucro_prejuízo
H2: LUCRO TOTAL
H4: =SUM(E4-C4) -> 1.66
H5: =SUM(E5-C5) -> -4.37
H6: =SUM(E6-C6) -> -3.87
H7: =SUM(E7-C7) -> 0.34
H8: =SUM(E8-C8) -> 16.52
H9: =SUM(E9-C9) -> -2.63
H10: =SUM(E10-C10) -> 7.65

Sheet gráficos
